cli_pybench-0.1.2.dist-info/licenses/LICENSE
pybench/__init__.py
pybench/_bench.py
pybench/_metadata.py
pybench/cli.py
pybench/py.typed
cli_pybench-0.1.2.dist-info/METADATA
cli_pybench-0.1.2.dist-info/WHEEL
cli_pybench-0.1.2.dist-info/entry_points.txt
cli_pybench-0.1.2.dist-info/top_level.txt
cli_pybench-0.1.2.dist-info/RECORD
