Metadata-Version: 2.4
Name: cli-pybench
Version: 0.1.2
Summary: A pytest-like framework for benchmarking
Author-email: Cangyuan Li <everest229@gmail.com>
License-Expression: MIT
Project-URL: Homepage, https://github.com/CangyuanLi/cli-pybench
Project-URL: Source, https://github.com/CangyuanLi/cli-pybench
Project-URL: Bug Reports, https://github.com/CangyuanLi/cli-pybench/issues
Classifier: Programming Language :: Python :: 3
Requires-Python: >=3.9
License-File: LICENSE
Requires-Dist: polars>=1.0.0
Requires-Dist: tomli
Requires-Dist: tqdm
Dynamic: license-file
